hydra_plugins/hydra_ray_launcher/__init__.py
hydra_plugins/hydra_ray_launcher/_config.py
hydra_plugins/hydra_ray_launcher/_core.py
hydra_plugins/hydra_ray_launcher/_core_aws.py
hydra_plugins/hydra_ray_launcher/_launcher_util.py
hydra_plugins/hydra_ray_launcher/_remote_invoke.py
hydra_plugins/hydra_ray_launcher/py.typed
hydra_plugins/hydra_ray_launcher/ray_aws_launcher.py
hydra_plugins/hydra_ray_launcher/ray_launcher.py
hydra_ray_launcher-1.2.1.dist-info/METADATA
hydra_ray_launcher-1.2.1.dist-info/WHEEL
hydra_ray_launcher-1.2.1.dist-info/top_level.txt
hydra_ray_launcher-1.2.1.dist-info/RECORD
