Metadata-Version: 2.1
Name: hydra-ray-launcher
Version: 1.2.1
Summary: Hydra Ray launcher plugin
Home-page: https://github.com/facebookresearch/hydra/
Author: Jieru Hu
Author-email: jieru@fb.com
Classifier: License :: OSI Approved :: MIT License
Classifier: Programming Language :: Python :: 3.7
Classifier: Programming Language :: Python :: 3.8
Classifier: Programming Language :: Python :: 3.9
Classifier: Programming Language :: Python :: 3.10
Classifier: Programming Language :: Python :: 3.11
Classifier: Operating System :: MacOS
Classifier: Operating System :: POSIX :: Linux
Requires-Dist: boto3
Requires-Dist: hydra-core >=1.1.2
Requires-Dist: ray[default] <3
Requires-Dist: aiohttp <4
Requires-Dist: cloudpickle <3
Requires-Dist: pickle5 ==0.0.12 ; python_version < "3.8"
